batch4py/__init__.py
batch4py/config.yml
batch4py/constants.py
batch4py/dependency.py
batch4py/job.py
batch4py/jobchain.py
batch4py/none.py
batch4py/scheduler.py
batch4py-0.2.4.dist-info/METADATA
batch4py-0.2.4.dist-info/RECORD
batch4py-0.2.4.dist-info/WHEEL
batch4py-0.2.4.dist-info/top_level.txt
