Metadata-Version: 2.1
Name: batch4py
Version: 0.2.4
Summary: Programmatic interface to batch schedulers.
Home-page: https://github.com/TerraFusion/batch4py
Author: Landon T. Clipp
Author-email: clipp2@illinois.edu
License: UNKNOWN
Download-URL: https://github.com/TerraFusion/batch4py/archive/0.2.4.tar.gz
Keywords: batch,torque,pbs,pbs-torque,hpc,python,python3,cluster,scheduler,schedule
Platform: UNKNOWN
Requires-Dist: pyyaml
